ssl_pinning_remover/__init__.py
ssl_pinning_remover/ssl_pinning_remover.py
ssl_pinning_remover/core/__init__.py
ssl_pinning_remover/core/core.py
ssl_pinning_remover/tools/new-release-key.keystore
ssl_pinning_remover/tools/zipalign
ssl_pinning_remover-1.0.0.dist-info/LICENSE
ssl_pinning_remover-1.0.0.dist-info/METADATA
ssl_pinning_remover-1.0.0.dist-info/WHEEL
ssl_pinning_remover-1.0.0.dist-info/entry_points.txt
ssl_pinning_remover-1.0.0.dist-info/top_level.txt
ssl_pinning_remover-1.0.0.dist-info/RECORD
