Metadata-Version: 2.1
Name: ssl-pinning-remover
Version: 1.0.0
Summary: An SSL Pinning Remover for Android Apps
Home-page: https://github.com/HexNio/ssl_pinning_remover
Author: HexNio
Author-email: 
License: UNKNOWN
Keywords: Android,beautifulsoup4,Bug Bounty,SSL Pinning,automation
Platform: UNKNOWN
Classifier: Programming Language :: Python :: 3 :: Only
Classifier: License :: OSI Approved :: GNU General Public License v3 (GPLv3)
Classifier: Operating System :: MacOS :: MacOS X
Classifier: Intended Audience :: Other Audience
Classifier: Intended Audience :: Education
Classifier: Operating System :: Android
Classifier: Topic :: Internet
Requires-Python: >=3.6
Requires-Dist: lxml
Requires-Dist: python-magic
Requires-Dist: beautifulsoup4
